query_blocker/__init__.py
query_blocker/query_blocker.py
django_query_blocker-0.0.1.dist-info/LICENSE
django_query_blocker-0.0.1.dist-info/METADATA
django_query_blocker-0.0.1.dist-info/WHEEL
django_query_blocker-0.0.1.dist-info/top_level.txt
django_query_blocker-0.0.1.dist-info/RECORD
