Metadata-Version: 2.1
Name: django-query-blocker
Version: 0.0.1
Summary: Blocks any DB query from being executed within the context.
Home-page: https://github.com/nano-labs/django-query-blocker
Download-URL: https://github.com/nano-labs/django-query-blocker/archive/0.0.1.zip
Author: Fabio Pachelli Pacheco
Author-email: nanook.labs@gmail.com
License: MIT
Keywords: django query block debug
Classifier: Development Status :: 3 - Alpha
Classifier: Intended Audience :: Developers
Classifier: Topic :: Software Development :: Build Tools
Classifier: License :: OSI Approved :: MIT License
Classifier: Programming Language :: Python :: 3.6
License-File: LICENSE
